xensieve-0.8.0.dist-info/METADATA
xensieve-0.8.0.dist-info/WHEEL
xensieve-0.8.0.dist-info/license_files/LICENSE
xensieve/__init__.py
xensieve/__init__.pyi
xensieve/py.typed
xensieve/xensieve.cp38-win_amd64.pyd
xensieve-0.8.0.dist-info/RECORD
