Metadata-Version: 2.3
Name: xensieve
Version: 0.8.0
Classifier: Development Status :: 5 - Production/Stable
Classifier: Topic :: Scientific/Engineering :: Mathematics
Classifier: Topic :: Artistic Software
Classifier: Programming Language :: Rust
Classifier: Programming Language :: Python :: Implementation :: CPython
Classifier: Programming Language :: Python :: Implementation :: PyPy
Classifier: Typing :: Typed
License-File: LICENSE
Summary: An Rust-backed implementation of the Xenakis Sieve
Keywords: sieve,residual,modulus,set,xenakis
Author: Christopher Ariza
Maintainer: Christopher Ariza
Requires-Python: >=3.8
Project-URL: Homepage, https://github.com/flexatone/xensieve-py
Project-URL: Repository, https://github.com/flexatone/xensieve-py.git
Project-URL: Issues, https://github.com/flexatone/xensieve-py/issues
